LICENSE
MANIFEST.in
README.md
setup.cfg
setup.py
versioneer.py
matplotlibhelper/__init__.py
matplotlibhelper/_version.py
matplotlibhelper/matplotlib_helper.py
matplotlibhelper.egg-info/PKG-INFO
matplotlibhelper.egg-info/SOURCES.txt
matplotlibhelper.egg-info/dependency_links.txt
matplotlibhelper.egg-info/requires.txt
matplotlibhelper.egg-info/top_level.txt
matplotlibhelper/fonts/MJ-Bold.otf
matplotlibhelper/fonts/MJ-Italic.otf
matplotlibhelper/fonts/MJ-OFL.txt
matplotlibhelper/fonts/MJ-Regular.otf
matplotlibhelper/fonts/MJ_Cal-Bold.otf
matplotlibhelper/fonts/MJ_Cal-Regular.otf
matplotlibhelper/fonts/MJ_Mat-BoldItalic.otf
matplotlibhelper/fonts/MJ_Mat-Italic.otf
matplotlibhelper/fonts/MJ_Mat-Regular.otf
matplotlibhelper/fonts/RobotizationMono-Apache2.txt
matplotlibhelper/fonts/RobotizationMono-Bold.ttf
matplotlibhelper/fonts/RobotizationMono-BoldItalic.ttf
matplotlibhelper/fonts/RobotizationMono-Italic.ttf
matplotlibhelper/fonts/RobotizationMono-Medium.ttf
matplotlibhelper/fonts/RobotizationMono-MediumItalic.ttf
matplotlibhelper/fonts/RobotizationMono-Regular.ttf
matplotlibhelper/fonts/STIXTwo-OFL.txt
matplotlibhelper/fonts/STIXTwoMath.otf
matplotlibhelper/fonts/STIXTwoText-Bold.otf
matplotlibhelper/fonts/STIXTwoText-BoldItalic.otf
matplotlibhelper/fonts/STIXTwoText-Italic.otf
matplotlibhelper/fonts/STIXTwoText-Regular.otf