Metadata-Version: 2.1
Name: matplotlibhelper
Version: 0.0.9
Summary: Matplotlib Helper is my custom helper to tune Matplotlib experience in Atom/Hydrogen and Pandoctools/Knitty.
Home-page: https://github.com/kiwi0fruit/matplotlibhelper
Author: Peter Zagubisalo
Author-email: peter.zagubisalo@gmail.com
License: MIT
Platform: UNKNOWN
Classifier: Development Status :: 3 - Alpha
Classifier: Intended Audience :: Developers
Classifier: Topic :: Software Development :: Build Tools
Classifier: License :: OSI Approved :: MIT License
Classifier: Programming Language :: Python :: 3
Classifier: Programming Language :: Python :: 3.6
Requires-Python: >=3.6
